zope/untrustedpython/__init__.py
zope/untrustedpython/builtins.py
zope/untrustedpython/interpreter.py
zope/untrustedpython/rcompile.py
zope/untrustedpython/tests.py
zope/untrustedpython/transformer.py
zope_untrustedpython-7.0.dist-info/METADATA
zope_untrustedpython-7.0.dist-info/WHEEL
zope_untrustedpython-7.0.dist-info/top_level.txt
zope_untrustedpython-7.0.dist-info/zip-safe
zope_untrustedpython-7.0.dist-info/RECORD
